inference_logic/__init__.py
inference_logic/algorithms.py
inference_logic/data_structures.py
inference_logic/equality.py
inference_logic-0.1.0.dist-info/AUTHORS.rst
inference_logic-0.1.0.dist-info/LICENSE
inference_logic-0.1.0.dist-info/METADATA
inference_logic-0.1.0.dist-info/WHEEL
inference_logic-0.1.0.dist-info/top_level.txt
inference_logic-0.1.0.dist-info/RECORD
