Metadata-Version: 2.1
Name: inference-logic
Version: 0.1.0
Summary: declarative programming on json-like objects in Python
Home-page: https://github.com/gecBurton/inference_logic
Author: George EC Burton
Author-email: g.e.c.burton@gmail.com
License: MIT license
Keywords: inference_logic
Platform: UNKNOWN
Classifier: Development Status :: 2 - Pre-Alpha
Classifier: Intended Audience :: Developers
Classifier: License :: OSI Approved :: MIT License
Classifier: Natural Language :: English
Classifier: Programming Language :: Python :: 3
Classifier: Programming Language :: Python :: 3.5
Classifier: Programming Language :: Python :: 3.6
Classifier: Programming Language :: Python :: 3.7
Classifier: Programming Language :: Python :: 3.8
Requires-Python: >=3.5
